{
  "source": "https://hmaal.com/gulab-jamun/",
  "totals": {
    "m3u8": 0,
    "mpd": 0,
    "total": 0
  },
  "hls": {
    "count": 0,
    "urls": []
  },
  "dash": {
    "count": 0,
    "urls": []
  },
  "debug": {
    "totalRequests": 2,
    "sampleRequests": [
      {
        "url": "https://video.maalcdn.com/Boom%20Movies/Gulab%20Jamun.mp4",
        "type": "media",
        "status": 206
      },
      {
        "url": "https://video.maalcdn.com/Boom%20Movies/Gulab%20Jamun.mp4",
        "type": "media",
        "status": 206
      }
    ]
  },
  "timestamp": "2026-02-03T08:02:02.450Z"
}